AUTHORS.rst
LICENSE
MANIFEST.in
README.rst
pyproject.toml
setup.cfg
setup.py
firedrake/__future__.py
firedrake/__init__.py
firedrake/_deprecation.py
firedrake/_version.py
firedrake/assemble.py
firedrake/assign.py
firedrake/bcs.py
firedrake/checkpointing.py
firedrake/cofunction.py
firedrake/configuration.py
firedrake/constant.py
firedrake/dmhooks.py
firedrake/eigensolver.py
firedrake/embedding.py
firedrake/ensemble.py
firedrake/evaluate.h
firedrake/exceptions.py
firedrake/extrusion_utils.py
firedrake/formmanipulation.py
firedrake/function.py
firedrake/functionspace.py
firedrake/functionspacedata.py
firedrake/functionspaceimpl.py
firedrake/halo.py
firedrake/interpolation.py
firedrake/linear_solver.py
firedrake/locate.c
firedrake/logging.py
firedrake/matrix.py
firedrake/mesh.py
firedrake/norms.py
firedrake/nullspace.py
firedrake/parameters.py
firedrake/parloops.py
firedrake/petsc.py
firedrake/pointeval_utils.py
firedrake/pointquery_utils.py
firedrake/progress_bar.py
firedrake/projection.py
firedrake/randomfunctiongen.py
firedrake/solving.py
firedrake/solving_utils.py
firedrake/supermeshing.py
firedrake/tsfc_interface.py
firedrake/ufl_expr.py
firedrake/utility_meshes.py
firedrake/utils.py
firedrake/variational_solver.py
firedrake/vector.py
firedrake/version.py
firedrake.egg-info/PKG-INFO
firedrake.egg-info/SOURCES.txt
firedrake.egg-info/dependency_links.txt
firedrake.egg-info/entry_points.txt
firedrake.egg-info/requires.txt
firedrake.egg-info/top_level.txt
firedrake/_check/__init__.py
firedrake/_check/tests/firedrake/conftest.py
firedrake/_check/tests/firedrake/regression/test_dg_advection.py
firedrake/_check/tests/firedrake/regression/test_interpolate_cross_mesh.py
firedrake/_check/tests/firedrake/regression/test_locate_cell.py
firedrake/_check/tests/firedrake/regression/test_matrix_free.py
firedrake/_check/tests/firedrake/regression/test_nullspace.py
firedrake/_check/tests/firedrake/regression/test_stokes_mini.py
firedrake/_check/tests/firedrake/supermesh/test_assemble_mixed_mass_matrix.py
firedrake/adjoint/__init__.py
firedrake/adjoint/ensemble_reduced_functional.py
firedrake/adjoint/ufl_constraints.py
firedrake/adjoint_utils/__init__.py
